ProgCtr.sv
// Project Name:   CSE141L
// Module Name:    ProgCtr
// Description:    instruction fetch (pgm ctr) for processor
//
// Revision:       2019.01.27
// Last Update:    2022.01.13

// These are **examples** of signals in some processor designs.
// In particular, your branch and target logic may vary.
//
// Parameters:
//  A: Number of address bits in instruction memory
module ProgCtr #(parameter A=10)(
  input                Reset,       // reset, init, etc. -- force PC to 0
                       Start,       // begin next program in series (request issued by test bench)
                       Clk,         // PC can change on pos. edges only
                       //BranchAbsEn, // jump unconditionally to Target value
                       //BranchRelEn, // jump conditionally to Target + PC
                       Branch,
                       ALU_flag,    // flag from ALU, e.g. Zero, Carry, Overflow, Negative (from ARM)
  input        [A-1:0] Target,      // jump ... "how high?"
  output logic [A-1:0] ProgCtr      // the program counter register itself
);


logic [1:0] StartCount;
logic start_r;

// program counter can clear to 0, increment, or jump
always_ff @(posedge Clk) begin
  if(Reset)
    ProgCtr <= 0;                  // for first program; want different value for 2nd or 3rd
  else if(Branch)             // unconditional absolute jump
    ProgCtr <= Target;             //   how would you make it conditional and/or relative?
  /*else if(BranchRelEn && ALU_flag) // conditional relative jump
    ProgCtr <= Target + ProgCtr;*/   //   how would you make it unconditional and/or absolute
  else
    ProgCtr <= ProgCtr+'b1;        // default increment (no need for ARM/MIPS +4 -- why?)

  // Note about Start:
  //
  // If your programs are spread out, with a gap in your machine code listing,
  // you will want to make Start cause an appropriate jump.
  //
  // If your programs are packed sequentially, such that program 2 begins right
  // after Program 1 ends, then you won't need to do anything special here.

  // Handle the Start signal by overriding normal behavior
  if (Reset) begin
    StartCount <= '0;
    start_r <= '0;
  end else begin
    start_r <= Start;
    // Detect rising edge of Start
    if ((start_r == '0) && (Start == '1)) begin
      StartCount <= StartCount + 1'b1;
    end
    // Detect falling edge of Start
    if ((start_r == '1) && (Start == '0)) begin
      case (StartCount)
        1: ProgCtr <= 'd000;
        2: ProgCtr <= 'd100;
        3: ProgCtr <= 'd200;
        default: ProgCtr <= ProgCtr;
      endcase
    end
    // And generally, don't let things go anywhere until first Start
    if (StartCount == '0)
      ProgCtr <= ProgCtr;
  end
end

endmodule

program2/ProgCtr_tb.sv
// Test bench
// Program Counter (Instruction Fetch)

module ProgCtr_tb;

timeunit 1ns/1ps;

// Define signals to interface with UUT
bit Reset;
bit Start;
bit Clk;
//bit BranchAbsEn;
//bit BranchRelEn;
bit Branch;
bit ALU_flag;
bit [9:0] TargetOrOffset;
logic [9:0] NextInstructionIndex;

// Instatiate and connect the Unit Under Test
ProgCtr uut (
  .Reset(Reset),
  .Start(Start),
  .Clk(Clk),
  //.BranchAbsEn(BranchAbsEn),
  //.BranchRelEn(BranchRelEn),
  .Branch(Branch),
  .ALU_flag(ALU_flag),
  .Target(TargetOrOffset),
  .ProgCtr(NextInstructionIndex)
);

integer ClockCounter = 0;
always @(posedge Clk)
  ClockCounter <= ClockCounter + 1;

// The actual testbench logic
//
// In this testbench, let's look at 'manual clocking'
initial begin
  // Time 0 values
  $display("Initialize Testbench.");
  Reset = '1;
  Start = '0;
  Clk = '0;
  Branch = '0;
  ALU_flag = '0;
  TargetOrOffset = '0;

  // Advance to simulation time 1, latch values
  #1 Clk = '1;

  // Advance to simulation time 2, check results, prepare next values
  #1 Clk = '0;
  $display("Checking Reset behavior");
  assert (NextInstructionIndex == 'd0);
  Reset = '0;

  // Advance to simulation time 3, latch values
  #1 Clk = '1;

  // Advance to simulation time 4, check results, prepare next values
  #1 Clk = '0;
  $display("Checking that nothing happens before Start");
  assert (NextInstructionIndex == 'd0);
  Start = '1;

  // Advance to simulation time 5, latch values
  #1 Clk = '1;

  // Advance to simulation time 6, check results, prepare next values
  #1 Clk = '0;
  $display("Checking that nothing happened during Start");
  assert (NextInstructionIndex == 'd0);
  Start = '0;

  // Advance to simulation time 7, latch values
  #1 Clk = '1;

  // Advance to simulation time 8, check outputs, prepare next values
  #1 Clk = '0;
  $display("Checking that first Start went to first program");
  assert (NextInstructionIndex == 'd000);
  // No change in inputs

  // Advance to simulation time 9, latch values
  #1 Clk = '1;

  // Advance to simulation time 10, check outputs, prepare next values
  #1 Clk = '0;
  $display("Checking that no branch advanced by 1");
  assert (NextInstructionIndex == 'd001);
  Branch = '1;
  TargetOrOffset = 'd10;

  // Latch, check, setup next test
  #1 Clk = '1;
  #1 Clk = '0;
  $display("Checking that branch went to target");
  assert (NextInstructionIndex == 'd10);
  /*BranchAbsEn = '0;
  BranchRelEn = '1;
  TargetOrOffset = 'd5;
  // note, ALU_flag still 0

  // Latch, check, setup next test
  #1 Clk = '1;
  #1 Clk = '0;
  $display("Checking that relative branch with no ALU flag did not jump");
  assert (NextInstructionIndex == 'd11);
  BranchAbsEn = '0;
  BranchRelEn = '1;
  TargetOrOffset = 'd5;
  ALU_flag = '1;

  // Latch, check, setup next test
  #1 Clk = '1;
  #1 Clk = '0;
  $display("Checking that relative branch with ALU flag did jump");
  assert (NextInstructionIndex == 'd16);*/

  $display("All checks passed.");
end

initial begin
  $dumpfile("ProgCtr.vcd");
  $dumpvars();
  $dumplimit(104857600); // 2**20*100 = 100 MB, plenty.
end

endmodule

ProgCtr.vcd
$date
	Mon May  9 11:30:05 2022
$end
$version
	Questa Intel Starter FPGA Edition Version 2021.2
$end
$timescale
	1ps
$end

$scope module ProgCtr_tb $end
$var reg 1 ! Reset $end
$var reg 1 " Start $end
$var reg 1 # Clk $end
$var reg 1 $ Branch $end
$var reg 1 % ALU_flag $end
$var reg 10 & TargetOrOffset [9:0] $end
$var reg 10 ' NextInstructionIndex [9:0] $end
$var integer 32 ( ClockCounter $end

$scope module uut $end
$var parameter 32 ) A $end
$var wire 1 * Reset $end
$var wire 1 + Start $end
$var wire 1 , Clk $end
$var wire 1 - Branch $end
$var wire 1 . ALU_flag $end
$var wire 1 / Target [9] $end
$var wire 1 0 Target [8] $end
$var wire 1 1 Target [7] $end
$var wire 1 2 Target [6] $end
$var wire 1 3 Target [5] $end
$var wire 1 4 Target [4] $end
$var wire 1 5 Target [3] $end
$var wire 1 6 Target [2] $end
$var wire 1 7 Target [1] $end
$var wire 1 8 Target [0] $end
$var reg 10 9 ProgCtr [9:0] $end
$var reg 2 : StartCount [1:0] $end
$var reg 1 ; start_r $end
$upscope $end
$upscope $end

$scope begin std $end
$upscope $end
$enddefinitions $end
#0
$dumpvars
1!
0"
0#
0$
0%
b0 &
bx '
bx 9
bx :
x;
b1010 )
b0 (
08
07
06
05
04
03
02
01
00
0/
0.
0-
0,
0+
1*
$end
#1000
1#
1,
b0 9
b0 :
0;
b1 (
b0 '
#2000
0#
0!
0*
0,
#3000
1#
1,
b1 9
b0 9
b10 (
#4000
0#
1"
1+
0,
#5000
1#
1,
b1 9
1;
b1 :
b0 9
b11 (
#6000
0#
0"
0+
0,
#7000
1#
1,
b1 9
0;
b0 9
b100 (
#8000
0#
0,
#9000
1#
1,
b1 9
b101 (
b1 '
#10000
0#
1$
b1010 &
1-
17
15
0,
#11000
1#
1,
b1010 9
b110 (
b1010 '
